django_db_utilities/__init__.py
django_db_utilities/apps.py
django_db_utilities/docs/commands.md
django_db_utilities/docs/configuration.md
django_db_utilities/docs/index.md
django_db_utilities/docs/installation.md
django_db_utilities/management/commands/delete_model_data.py
django_db_utilities/management/commands/reset_database.py
django_db_utilities/management/commands/reset_primary_keys.py
django_db_utilities-0.1.5.dist-info/LICENSE
django_db_utilities-0.1.5.dist-info/METADATA
django_db_utilities-0.1.5.dist-info/WHEEL
django_db_utilities-0.1.5.dist-info/RECORD
